micropython_mmc5983/__init__.py
micropython_mmc5983/i2c_helpers.py
micropython_mmc5983/mmc5983.py
micropython_mmc5983-0.1.0.dist-info/LICENSE
micropython_mmc5983-0.1.0.dist-info/METADATA
micropython_mmc5983-0.1.0.dist-info/WHEEL
micropython_mmc5983-0.1.0.dist-info/top_level.txt
micropython_mmc5983-0.1.0.dist-info/RECORD
