Metadata-Version: 2.1
Name: micropython-mmc5983
Version: 0.1.0
Summary: MicroPython Library for the Memsic MMC5983 Magnetometer
Author-email: JDM <xxyx@mailmeto.mozmail.com>
License: MIT
Project-URL: Homepage, https://github.com/jposada202020/MicroPython_MMC5983
Keywords: sensor,micropython,mmc5983,micropython,driver,sensor,magnetometer,mmc5983
Classifier: Intended Audience :: Developers
Classifier: Topic :: Software Development :: Libraries
Classifier: Topic :: Software Development :: Embedded Systems
Classifier: Topic :: System :: Hardware
Classifier: License :: OSI Approved :: MIT License
Classifier: Programming Language :: Python :: Implementation :: MicroPython
License-File: LICENSE
